Metadata-Version: 2.1
Name: onnlogger
Version: 0.0.5
Summary: Convenience module for logging
Home-page: http://oznetnerd.com
Author: Will Robinson
Author-email: will@oznetnerd.com
License: UNKNOWN
Platform: UNKNOWN
